GuessRandomNo/Guess.py
GuessRandomNo/__init__.py
GuessRandomNo-0.3.2.dist-info/METADATA
GuessRandomNo-0.3.2.dist-info/WHEEL
GuessRandomNo-0.3.2.dist-info/top_level.txt
GuessRandomNo-0.3.2.dist-info/RECORD
