Metadata-Version: 2.1
Name: GuessRandomNo
Version: 0.3.2
Summary: Random Number Package
Home-page: UNKNOWN
Author: Dhiraj Tembulkar
Author-email: tembulkardhiraj@gmail.com
License: UNKNOWN
Keywords: python
Platform: UNKNOWN
Classifier: Development Status :: 3 - Alpha
Classifier: Intended Audience :: Education
Classifier: Programming Language :: Python :: 2
Classifier: Programming Language :: Python :: 3
Classifier: Operating System :: MacOS :: MacOS X
Classifier: Operating System :: Microsoft :: Windows
